{"_type":"export","__export_format":4,"__export_date":"2025-02-11T04:43:45.535Z","__export_source":"insomnia.desktop.app:v2023.5.8","resources":[{"_id":"req_0bbfb9364bd8405db3c9fba6874c8d77","parentId":"wrk_85ee853d5468408a88ff25c01bbe45e5","modified":1739203524236,"created":1739126220249,"url":"http://localhost:8080/api/clientes/add","name":"01 POST CLIENTE","description":"","method":"POST","body":{"mimeType":"application/json","text":"{\n        \"persona\": {\n        \"nombre\": \"Juan Osorio\",\n        \"identificacion\": \"1111111111\",\n        \"direccion\": \"13 junio y Equinoccial\",\n        \"telefono\": \"098874587\"\n        },\n        \"edad\": 32,\n        \"genero\": \"Masculino\",\n        \"password\": \"1245\",\n        \"estado\": true\n}\n"},"parameters":[],"headers":[{"name":"Content-Type","value":"application/json"},{"name":"User-Agent","value":"insomnia/2023.5.8","id":"pair_08901480adec409dae8021a62022727a"}],"authentication":{},"metaSortKey":-1739126220249,"isPrivate":false,"settingStoreCookies":true,"settingSendCookies":true,"settingDisableRenderRequestBody":false,"settingEncodeUrl":true,"settingRebuildPath":true,"settingFollowRedirects":"global","_type":"request"},{"_id":"wrk_85ee853d5468408a88ff25c01bbe45e5","parentId":null,"modified":1739126199210,"created":1739126199210,"name":"Banco","description":"","scope":"collection","_type":"workspace"},{"_id":"req_63f53bbe78f64e759c24bb954f8f8f58","parentId":"wrk_85ee853d5468408a88ff25c01bbe45e5","modified":1739141288233,"created":1739141238302,"url":"http://localhost:8080/api/clientes","name":"02 GET CLIENTES","description":"","method":"GET","body":{},"parameters":[],"headers":[{"name":"User-Agent","value":"insomnia/2023.5.8"}],"authentication":{},"metaSortKey":-1739126220149,"isPrivate":false,"settingStoreCookies":true,"settingSendCookies":true,"settingDisableRenderRequestBody":false,"settingEncodeUrl":true,"settingRebuildPath":true,"settingFollowRedirects":"global","_type":"request"},{"_id":"req_342863e2a49f40f489dff30795fcc2aa","parentId":"wrk_85ee853d5468408a88ff25c01bbe45e5","modified":1739141355590,"created":1739141337675,"url":"http://localhost:8080/api/clientes/11","name":"03 GET CLIENTE BY ID","description":"","method":"GET","body":{},"parameters":[],"headers":[{"name":"User-Agent","value":"insomnia/2023.5.8"}],"authentication":{},"metaSortKey":-1734294488943,"isPrivate":false,"settingStoreCookies":true,"settingSendCookies":true,"settingDisableRenderRequestBody":false,"settingEncodeUrl":true,"settingRebuildPath":true,"settingFollowRedirects":"global","_type":"request"},{"_id":"req_5487a155db024f6990d20e9ea4958ac7","parentId":"wrk_85ee853d5468408a88ff25c01bbe45e5","modified":1739145382134,"created":1739142922778,"url":"http://localhost:8080/api/cuentas/add","name":"04 POST CUENTA","description":"","method":"POST","body":{"mimeType":"application/json","text":"{\n        \"numeroCuenta\": \"585545\",\n        \"tipoCuenta\": \"CORRIENTE\",\n        \"saldoInicial\": 1000,\n        \"estado\": true,\n        \"clienteId\": 10\n}\n"},"parameters":[],"headers":[{"name":"Content-Type","value":"application/json"},{"name":"User-Agent","value":"insomnia/2023.5.8"}],"authentication":{},"metaSortKey":-1734294488843,"isPrivate":false,"settingStoreCookies":true,"settingSendCookies":true,"settingDisableRenderRequestBody":false,"settingEncodeUrl":true,"settingRebuildPath":true,"settingFollowRedirects":"global","_type":"request"},{"_id":"req_f3f2c6ccb6e348e8a456895a30829254","parentId":"wrk_85ee853d5468408a88ff25c01bbe45e5","modified":1739145567332,"created":1739145552192,"url":"http://localhost:8080/api/cuentas","name":"05 GET CUENTAS","description":"","method":"GET","body":{},"parameters":[],"headers":[{"name":"User-Agent","value":"insomnia/2023.5.8"}],"authentication":{},"metaSortKey":-1734294488743,"isPrivate":false,"settingStoreCookies":true,"settingSendCookies":true,"settingDisableRenderRequestBody":false,"settingEncodeUrl":true,"settingRebuildPath":true,"settingFollowRedirects":"global","_type":"request"},{"_id":"req_e59ab69156b848a5836733b5e65852ae","parentId":"wrk_85ee853d5468408a88ff25c01bbe45e5","modified":1739203488893,"created":1739145618200,"url":"http://localhost:8080/api/cuentas/cliente/10","name":"06 GET CUENTA BYCLIENTE","description":"","method":"GET","body":{},"parameters":[],"headers":[{"name":"User-Agent","value":"insomnia/2023.5.8"}],"authentication":{},"metaSortKey":-1734294488643,"isPrivate":false,"settingStoreCookies":true,"settingSendCookies":true,"settingDisableRenderRequestBody":false,"settingEncodeUrl":true,"settingRebuildPath":true,"settingFollowRedirects":"global","_type":"request"},{"_id":"req_015d58a79ce1451bb2e1f85025fda72f","parentId":"wrk_85ee853d5468408a88ff25c01bbe45e5","modified":1739244916545,"created":1739203502016,"url":"http://localhost:8080/api/movimientos/add","name":"07 POST MOVIMIENTO","description":"","method":"POST","body":{"mimeType":"application/json","text":"{\n        \"valor\": 1000,\n        \"numeroCuenta\": \"666666\",\n        \"tipoMovimiento\": \"RETIRO\"\n}\n"},"parameters":[],"headers":[{"name":"Content-Type","value":"application/json"},{"name":"User-Agent","value":"insomnia/2023.5.8"}],"authentication":{},"metaSortKey":-1734294488543,"isPrivate":false,"settingStoreCookies":true,"settingSendCookies":true,"settingDisableRenderRequestBody":false,"settingEncodeUrl":true,"settingRebuildPath":true,"settingFollowRedirects":"global","_type":"request"},{"_id":"req_8ada380a2759413ca90430f623b688e6","parentId":"wrk_85ee853d5468408a88ff25c01bbe45e5","modified":1739209136105,"created":1739208211939,"url":"http://localhost:8080/api/movimientos/cuenta/496825","name":"08 GET MOV BY CUENTA","description":"","method":"GET","body":{},"parameters":[],"headers":[{"name":"User-Agent","value":"insomnia/2023.5.8","id":"pair_4636a6970df740249dfa87dbd5afac06"},{"id":"pair_1f9e126f14a849abbd27dba1f4c159f8","name":"Content-Type","value":"application/json","description":""}],"authentication":{},"metaSortKey":-1734294488443,"isPrivate":false,"settingStoreCookies":true,"settingSendCookies":true,"settingDisableRenderRequestBody":false,"settingEncodeUrl":true,"settingRebuildPath":true,"settingFollowRedirects":"global","_type":"request"},{"_id":"req_33d741b2c6e949d0aabab3d071232dba","parentId":"wrk_85ee853d5468408a88ff25c01bbe45e5","modified":1739210295928,"created":1739208994118,"url":"http://localhost:8080/api/reportes?numeroCuenta=496825&fechaInicio=2025-02-10&fechaFin=2025-02-10","name":"09 REPORTE FECHAS #C","description":"","method":"GET","body":{},"parameters":[],"headers":[{"name":"User-Agent","value":"insomnia/2023.5.8","id":"pair_31a57c2fb4d44dc38ed270db9056b44f"},{"id":"pair_a200059779504ae88cb852a226b14f6e","name":"Content-Type","value":"application/json","description":""}],"authentication":{},"metaSortKey":-1734294488343,"isPrivate":false,"settingStoreCookies":true,"settingSendCookies":true,"settingDisableRenderRequestBody":false,"settingEncodeUrl":true,"settingRebuildPath":true,"settingFollowRedirects":"global","_type":"request"},{"_id":"req_b180b9b5d873411dbc6cc215da61ea8a","parentId":"wrk_85ee853d5468408a88ff25c01bbe45e5","modified":1739210340687,"created":1739210311022,"url":"http://localhost:8080/api/reportes/por-cedula?cedula=2222222222&fechaInicio=2025-02-10&fechaFin=2025-02-10","name":"10 REPORTE FECHAS Cedu","description":"","method":"GET","body":{},"parameters":[],"headers":[{"name":"User-Agent","value":"insomnia/2023.5.8","id":"pair_31a57c2fb4d44dc38ed270db9056b44f"},{"id":"pair_a200059779504ae88cb852a226b14f6e","name":"Content-Type","value":"application/json","description":""}],"authentication":{},"metaSortKey":-1731878623040,"isPrivate":false,"settingStoreCookies":true,"settingSendCookies":true,"settingDisableRenderRequestBody":false,"settingEncodeUrl":true,"settingRebuildPath":true,"settingFollowRedirects":"global","_type":"request"},{"_id":"req_4d1567f7006f43508557c6c18519f664","parentId":"wrk_85ee853d5468408a88ff25c01bbe45e5","modified":1739236215298,"created":1739236090813,"url":"http://localhost:8080/api/clientes/update/15","name":"11 EDITAR CLIENTEBYID","description":"","method":"PUT","body":{"mimeType":"application/json","text":"{\n  \"id\": 15,\n  \"persona\": {\n    \"id\": 15,\n    \"nombre\": \"PAULITO\",\n    \"identificacion\": \"2222222222\",\n    \"direccion\": \"casa\",\n    \"telefono\": \"999999999\"\n  },\n  \"edad\": 32,\n  \"genero\": \"Masculino\",\n  \"password\": \"1234\",\n  \"estado\": true\n}"},"parameters":[],"headers":[{"name":"Content-Type","value":"application/json"},{"name":"User-Agent","value":"insomnia/2023.5.8"}],"authentication":{},"metaSortKey":-1731878622940,"isPrivate":false,"settingStoreCookies":true,"settingSendCookies":true,"settingDisableRenderRequestBody":false,"settingEncodeUrl":true,"settingRebuildPath":true,"settingFollowRedirects":"global","_type":"request"},{"_id":"req_7f9ea529bc05402781409ad118ac3714","parentId":"wrk_85ee853d5468408a88ff25c01bbe45e5","modified":1739244262622,"created":1739236253848,"url":"http://localhost:8080/api/clientes/delete/23","name":"12 DELETE ONLY CLIENTE","description":"","method":"DELETE","body":{},"parameters":[],"headers":[{"name":"User-Agent","value":"insomnia/2023.5.8"}],"authentication":{},"metaSortKey":-1731878622840,"isPrivate":false,"settingStoreCookies":true,"settingSendCookies":true,"settingDisableRenderRequestBody":false,"settingEncodeUrl":true,"settingRebuildPath":true,"settingFollowRedirects":"global","_type":"request"},{"_id":"req_f0a4fa50b7cf4d8dbfb0ae31aec6e572","parentId":"wrk_85ee853d5468408a88ff25c01bbe45e5","modified":1739244297727,"created":1739244279732,"url":"http://localhost:8080/api/movimientos","name":"13 GET Movimientos","description":"","method":"GET","body":{},"parameters":[],"headers":[{"name":"User-Agent","value":"insomnia/2023.5.8"}],"authentication":{},"metaSortKey":-1731878622740,"isPrivate":false,"settingStoreCookies":true,"settingSendCookies":true,"settingDisableRenderRequestBody":false,"settingEncodeUrl":true,"settingRebuildPath":true,"settingFollowRedirects":"global","_type":"request"},{"_id":"env_bee9ef4a03253c0e5e22281a4483054fdf964f34","parentId":"wrk_85ee853d5468408a88ff25c01bbe45e5","modified":1739126199214,"created":1739126199214,"name":"Base Environment","data":{},"dataPropertyOrder":null,"color":null,"isPrivate":false,"metaSortKey":1739126199214,"_type":"environment"},{"_id":"jar_bee9ef4a03253c0e5e22281a4483054fdf964f34","parentId":"wrk_85ee853d5468408a88ff25c01bbe45e5","modified":1739126199215,"created":1739126199215,"name":"Default Jar","cookies":[],"_type":"cookie_jar"}]}